easysolc/__init__.py
easysolc/easysolc.py
easysolc-0.1.4.dist-info/METADATA
easysolc-0.1.4.dist-info/RECORD
easysolc-0.1.4.dist-info/WHEEL
easysolc-0.1.4.dist-info/top_level.txt
